forcedtypes
