Metadata-Version: 1.0
Name: forcedtypes
Version: 0.2
Summary: Force crappy data into python type.
Home-page: http://bfaludi.com
Author: Bence Faludi
Author-email: bence@ozmo.hu
License: GPL
Platform: UNKNOWN
